{
  "__inputs": [],
  "__requires": [],
  "annotations": {
    "list": [
      {
        "builtIn": 1,
        "datasource": {
          "type": "grafana",
          "uid": "-- Grafana --"
        },
        "enable": true,
        "hide": true,
        "iconColor": "rgba(0, 211, 255, 1)",
        "name": "Annotations & Alerts",
        "type": "dashboard"
      }
    ]
  },
  "editable": true,
  "gnetId": null,
  "graphTooltip": 0,
  "id": null,
  "links": [],
  "panels": [
    {
      "datasource": {
        "type": "loki",
        "uid": "Loki"
      },
      "gridPos": {
        "h": 24,
        "w": 24,
        "x": 0,
        "y": 0
      },
      "id": 2,
      "options": {
        "dedupStrategy": "none",
        "enableLogDetails": true,
        "prettifyLogMessage": false,
        "showCommonLabels": false,
        "showLabels": true,
        "showTime": true,
        "sortOrder": "Descending",
        "wrapLogMessage": true
      },
      "pluginVersion": "10.0.3",
      "targets": [
        {
          "datasource": {
            "type": "loki",
            "uid": "Loki"
          },
          "expr": "{compose_project=\"el-dorado-tanstack\"}",
          "refId": "A"
        }
      ],
      "title": "Log Explorer",
      "type": "logs"
    }
  ],
  "schemaVersion": 37,
  "style": "dark",
  "tags": [],
  "templating": {
    "list": []
  },
  "time": {
    "from": "now-1h",
    "to": "now"
  },
  "timepicker": {},
  "timezone": "",
  "title": "Loki Log Explorer",
  "uid": "loki-log-explorer",
  "version": 1
}